Flask_SlimREST-0.1.2.dist-info/DESCRIPTION.rst
Flask_SlimREST-0.1.2.dist-info/METADATA
Flask_SlimREST-0.1.2.dist-info/RECORD
Flask_SlimREST-0.1.2.dist-info/WHEEL
Flask_SlimREST-0.1.2.dist-info/metadata.json
Flask_SlimREST-0.1.2.dist-info/top_level.txt
flask_slimrest/__init__.py
flask_slimrest/__version__.py
flask_slimrest/decorators.py
flask_slimrest/exceptions.py
flask_slimrest/pagination.py
flask_slimrest/slim_rest.py
flask_slimrest/utils.py
